{
  "_fv": 17,
  "_type": "overlay",
  "definition": {
    "priority": "NORMAL",
    "components": [
      {
        "type": "image",
        "data": {
          "image": "ground.png",
          "use1Xscale": false,
          "name": "ground.png",
          "x": -1,
          "y": 169
        }
      },
      {
        "type": "image",
        "data": {
          "image": "rocketingui.png",
          "use1Xscale": false,
          "name": "rocketingui.png",
          "x": -1,
          "y": 162
        }
      }
    ],
    "baseTexture": "",
    "displayCondition": {
      "name": "CheckRocket1"
    }
  }
}